amethyst_core-0.9.0-nspkg.pth
amethyst/core/__init__.py
amethyst/core/obj.py
amethyst/core/util.py
amethyst_core-0.9.0.dist-info/LICENSE
amethyst_core-0.9.0.dist-info/METADATA
amethyst_core-0.9.0.dist-info/WHEEL
amethyst_core-0.9.0.dist-info/namespace_packages.txt
amethyst_core-0.9.0.dist-info/top_level.txt
amethyst_core-0.9.0.dist-info/RECORD
