Metadata-Version: 2.1
Name: amethyst-core
Version: 0.9.0
Summary: A sober python base library
Home-page: https://github.com/duelafn/python-amethyst-core
Author: Dean Serenevy
Author-email: dean@serenevy.net
License: UNKNOWN
Platform: UNKNOWN
Classifier: Development Status :: 4 - Beta
Classifier: Intended Audience :: Developers
Classifier: License :: OSI Approved :: GNU Lesser General Public License v3 (LGPLv3)
Classifier: Programming Language :: Python
Classifier: Programming Language :: Python :: 3
Classifier: Programming Language :: Python :: Implementation :: CPython
Classifier: Programming Language :: Python :: Implementation :: PyPy
Classifier: Operating System :: OS Independent
Classifier: Topic :: Software Development
